{"version":1,"resource":"file:///c%3A/Users/netya/Nextcloud/University/asm/asm_lab6/src/6-14-IM-34-Netyaga.asm","entries":[{"id":"EDur.asm","timestamp":1746444805058},{"id":"tyP8.asm","timestamp":1746444963850},{"id":"WKaO.asm","timestamp":1746444999605},{"id":"zXb1.asm","timestamp":1746445018569},{"id":"X2Z5.asm","timestamp":1746445768839},{"id":"Szoa.asm","timestamp":1746445892283},{"id":"1m1k.asm","timestamp":1746446009317},{"id":"I6tD.asm","timestamp":1746446110613},{"id":"TTHw.asm","timestamp":1746446178976},{"id":"xzyQ.asm","timestamp":1746446392554},{"id":"Hk49.asm","timestamp":1746446429744},{"id":"2GJE.asm","timestamp":1746446787044},{"id":"KBHJ.asm","timestamp":1746446870688},{"id":"XyI0.asm","timestamp":1746446914424},{"id":"KZ0g.asm","timestamp":1746446958924},{"id":"UfQi.asm","source":"undoRedo.source","timestamp":1746446978928},{"id":"W6zZ.asm","timestamp":1746446985263},{"id":"WrRK.asm","source":"undoRedo.source","timestamp":1746447047983},{"id":"D4Ln.asm","timestamp":1746447190052},{"id":"FfXW.asm","source":"undoRedo.source","timestamp":1746447196051},{"id":"ZaOG.asm","timestamp":1746447240845},{"id":"EJmf.asm","timestamp":1746447717083},{"id":"RiAm.asm","source":"undoRedo.source","timestamp":1746447891284},{"id":"7jWD.asm","timestamp":1746448202663},{"id":"jCVi.asm","timestamp":1746448257483},{"id":"IuIB.asm","timestamp":1746448330173},{"id":"4ioM.asm","source":"undoRedo.source","timestamp":1746448354404},{"id":"Dpob.asm","timestamp":1746448413304},{"id":"fqnS.asm","timestamp":1746448799845},{"id":"gqfy.asm","timestamp":1746448824553},{"id":"TrFV.asm","timestamp":1746448838346},{"id":"6mKc.asm","timestamp":1746448852134},{"id":"om23.asm","timestamp":1746448893144},{"id":"f3Ui.asm","source":"undoRedo.source","timestamp":1746448910385},{"id":"vS0Q.asm","timestamp":1746448976471},{"id":"m4lN.asm","timestamp":1746449005863},{"id":"Jvbf.asm","timestamp":1746449021811},{"id":"i4mN.asm","timestamp":1746449057860},{"id":"QYCY.asm","timestamp":1746449375803},{"id":"Evdy.asm","timestamp":1746449414265},{"id":"MYAi.asm","timestamp":1746449439769},{"id":"9xLr.asm","timestamp":1746449566315},{"id":"61YF.asm","timestamp":1746449642860},{"id":"tMCm.asm","source":"undoRedo.source","timestamp":1746449660676},{"id":"mcZO.asm","source":"undoRedo.source","timestamp":1746449672183},{"id":"0Iig.asm","timestamp":1746449726274},{"id":"yJrj.asm","timestamp":1746449860003},{"id":"QhgE.asm","timestamp":1746449877113},{"id":"fI3t.asm","timestamp":1746450163383},{"id":"ubxV.asm","timestamp":1746455016561}]}